{
  "projects": [
    {
      "name": "Teste 3",
      "budget": "2800",
      "category": {
        "id": "1",
        "name": "Infra"
      },
      "cost": 0,
      "services": [],
      "id": "vdlxF5ZSll8"
    },
    {
      "name": "Teste 4",
      "budget": "3455",
      "category": {
        "id": "2",
        "name": "Desenvolvimento"
      },
      "cost": 0,
      "services": [],
      "id": "f_CqDwBgOQI"
    }
  ],
  "categories": [
    {
      "id": "1",
      "name": "Infra"
    },
    {
      "id": "2",
      "name": "Desenvolvimento"
    },
    {
      "id": "3",
      "name": "Design"
    },
    {
      "id": "4",
      "name": "Planejamento"
    }
  ],
  "$schema": "./node_modules/json-server/schema.json"
}